Metadata-Version: 1.1
Name: Workon
Version: 0.7.1
Summary: Switch between projects quickly from command line
Home-page: https://github.com/henocdz/workon
Author: henocdz
Author-email: self@henocdz.com
License: MIT
Download-URL: https://github.com/henocdz/workon/tarball/0.7.1
Keywords: terminal side projects manager work cli
Platform: UNKNOWN
Classifier: Intended Audience :: Developers
Classifier: License :: OSI Approved :: MIT License
Classifier: Programming Language :: Python
